jl95/pytools/maven.py
jl95/pytools/mavenaccio.py
jl95/pytools/mavendeployfile.py
jl95/pytools/mavengithub.py
jl95/pytools/ppmaven.py
jl95/pytools/swmaven.py
jl95/pytools/vtmaven.py
jl95terceira/pytools/maven.py
jl95terceira/pytools/mavenaccio.py
jl95terceira/pytools/mavendeployfile.py
jl95terceira/pytools/mavengithub.py
jl95terceira/pytools/versionjm.py
jl95terceira_pytools_maven-0.5.4.dist-info/METADATA
jl95terceira_pytools_maven-0.5.4.dist-info/WHEEL
jl95terceira_pytools_maven-0.5.4.dist-info/entry_points.txt
jl95terceira_pytools_maven-0.5.4.dist-info/RECORD
