Metadata-Version: 2.4
Name: jl95terceira_pytools_maven
Version: 0.5.4
Summary: Python command line tools collection - Apache Maven
Project-URL: Homepage, https://github.com/jl95terceira/project-pytools-maven
Project-URL: Issues, https://github.com/jl95terceira/project-pytools-maven/issues
Author-email: Joao Luis Ornelas da Silva <jl95terceira@gmail.com>
Classifier: License :: OSI Approved :: MIT License
Classifier: Operating System :: OS Independent
Classifier: Programming Language :: Python :: 3
Requires-Python: >=3.12
Requires-Dist: jl95terceira-pytools-env-git>=0.1.3
Requires-Dist: jl95terceira-pytools-env-java>=0.2.8
Requires-Dist: jl95terceira-pytools-java>=0.1.2
Requires-Dist: jl95terceira-pytools>=1.2.1
